{
    "name": "retrieval_goal-0012.json",
    "ceilingMaterial": "AI2-THOR/Materials/Ceramics/GREYGRANITE",
    "floorMaterial": "AI2-THOR/Materials/Wood/WoodGrain_Brown",
    "wallMaterial": "AI2-THOR/Materials/Ceramics/GREYGRANITE",
    "performerStart": {
        "position": {
            "x": -0.42,
            "y": 0,
            "z": 4.14
        },
        "rotation": {
            "y": 270
        }
    },
    "objects": [
        {
            "id": "bb45d4ea-cf3b-46b5-be23-f4097b8db1c5",
            "type": "sphere",
            "info": [
                "tiny",
                "light",
                "orange",
                "plastic",
                "hollow",
                "ball",
                "tiny light orange plastic hollow ball"
            ],
            "mass": 0.0625,
            "dimensions": {
                "x": 0.025,
                "y": 0.025,
                "z": 0.025
            },
            "moveable": true,
            "pickupable": true,
            "shows": [
                {
                    "rotation": {
                        "x": 0.0,
                        "y": 0.0,
                        "z": 0.0
                    },
                    "position": {
                        "x": 0,
                        "y": -0.0585,
                        "z": -0.655
                    },
                    "bounding_box": [
                        {
                            "x": -2.0046446609406727,
                            "y": 0,
                            "z": -1.38
                        },
                        {
                            "x": -2.04,
                            "y": 0,
                            "z": -1.4153553390593272
                        },
                        {
                            "x": -2.0753553390593273,
                            "y": 0,
                            "z": -1.38
                        },
                        {
                            "x": -2.04,
                            "y": 0,
                            "z": -1.3446446609406726
                        }
                    ],
                    "stepBegin": 0,
                    "scale": {
                        "x": 0.025,
                        "y": 0.025,
                        "z": 0.025
                    }
                }
            ],
            "materials": [
                "AI2-THOR/Materials/Plastics/OrangePlastic"
            ],
            "salientMaterials": [
                "plastic",
                "hollow"
            ],
            "locationParent": "6232417f-4c0f-40b4-9282-d789c0b9a3f8"
        },
        {
            "id": "6232417f-4c0f-40b4-9282-d789c0b9a3f8",
            "type": "box_3",
            "info": [
                "tiny",
                "light",
                "paper",
                "brown",
                "box",
                "tiny light paper brown box"
            ],
            "mass": 0.25,
            "dimensions": {
                "x": 0.356,
                "y": 0.25,
                "z": 0.2515
            },
            "moveable": true,
            "pickupable": true,
            "receptacle": true,
            "openable": true,
            "shows": [
                {
                    "rotation": {
                        "x": 0,
                        "y": 315,
                        "z": 0
                    },
                    "position": {
                        "x": 2.616,
                        "y": 0.15,
                        "z": -2.7125
                    },
                    "bounding_box": [
                        {
                            "x": 3.049567369570828,
                            "y": 0,
                            "z": -2.8638926586339943
                        },
                        {
                            "x": 2.6938926586339944,
                            "y": 0,
                            "z": -3.219567369570828
                        },
                        {
                            "x": 2.1904326304291724,
                            "y": 0,
                            "z": -2.7161073413660057
                        },
                        {
                            "x": 2.546107341366006,
                            "y": 0,
                            "z": -2.3604326304291723
                        }
                    ],
                    "stepBegin": 0,
                    "scale": {
                        "x": 0.5,
                        "y": 0.5,
                        "z": 0.5
                    }
                }
            ],
            "salientMaterials": [
                "paper"
            ]
        },
        {
            "id": "trophy",
            "type": "trophy",
            "shows": [
                {
                    "stepBegin": 0,
                    "position": {
                        "x": -2.5833650592798776,
                        "y": 0.08,
                        "z": 1.9579905477531154
                    },
                    "rotation": {
                        "x": 90,
                        "y": 180,
                        "z": 0
                    }
                }
            ]
        },
        {
            "id": "treasure_chest_small",
            "type": "chest_2",
            "salientMaterials": [
                "metal"
            ],
            "materials": [
                "AI2-THOR/Materials/Metals/BrownMetal 1"
            ],
            "shows": [
                {
                    "stepBegin": 0,
                    "position": {
                        "x": 3.0361490068798744,
                        "y": 0,
                        "z": 1.6653284010389067
                    },
                    "rotation": {
                        "x": 0,
                        "y": 180,
                        "z": 0
                    },
                    "scale": {
                        "x": 0.3,
                        "y": 0.3,
                        "z": 0.3
                    }
                }
            ]
        },
        {
            "id": "treasure_chest_med",
            "type": "chest_2",
            "salientMaterials": [
                "plastic"
            ],
            "materials": [
                "UnityAssetStore/Kindergarten_Interior/Models/Materials/color 2"
            ],
            "shows": [
                {
                    "stepBegin": 0,
                    "position": {
                        "x": 0,
                        "y": 0,
                        "z": 1.5
                    },
                    "rotation": {
                        "x": 0,
                        "y": 180,
                        "z": 0
                    },
                    "scale": {
                        "x": 0.7,
                        "y": 0.7,
                        "z": 0.7
                    }
                }
            ]
        }
    ],
    "goal": {
        "category": "retrieval",
        "description": "Find and pick up the trophy.",
        "last_step": 3000,
        "metadata": {
            "target": {
                "id": "trophy",
                "image": null
            }
        }
    },
    "answer": {}
}