{
    "name": "retrieval_goal-0113.json",
    "ceilingMaterial": "AI2-THOR/Materials/Walls/DrywallBeige",
    "floorMaterial": "AI2-THOR/Materials/Walls/EggshellDrywall",
    "wallMaterial": "AI2-THOR/Materials/Walls/DrywallBeige",
    "performerStart": {
        "position": {
            "x": 0.69,
            "y": 0,
            "z": -0.15
        },
        "rotation": {
            "y": 225
        }
    },
    "objects": [
        {
            "id": "58b74cff-ec0a-40f6-838e-f95789263440",
            "type": "plate_1",
            "info": [
                "tiny",
                "light",
                "blue",
                "plastic",
                "plate",
                "tiny light blue plastic plate"
            ],
            "mass": 0.25,
            "dimensions": {
                "x": 0.208,
                "y": 0.117,
                "z": 0.222
            },
            "moveable": true,
            "pickupable": true,
            "stackTarget": true,
            "shows": [
                {
                    "rotation": {
                        "x": 0,
                        "y": 0,
                        "z": 0
                    },
                    "position": {
                        "x": 2.22,
                        "y": 0.005,
                        "z": 1.51
                    },
                    "bounding_box": [
                        {
                            "x": 2.4280000000000004,
                            "y": 0,
                            "z": 1.732
                        },
                        {
                            "x": 2.4280000000000004,
                            "y": 0,
                            "z": 1.288
                        },
                        {
                            "x": 2.012,
                            "y": 0,
                            "z": 1.288
                        },
                        {
                            "x": 2.012,
                            "y": 0,
                            "z": 1.732
                        }
                    ],
                    "stepBegin": 0,
                    "scale": {
                        "x": 1,
                        "y": 1,
                        "z": 1
                    }
                }
            ],
            "materials": [
                "UnityAssetStore/Kindergarten_Interior/Models/Materials/color 2"
            ],
            "salientMaterials": [
                "plastic"
            ]
        },
        {
            "id": "trophy",
            "type": "trophy",
            "shows": [
                {
                    "stepBegin": 0,
                    "position": {
                        "x": -1.1566649585316968,
                        "y": 0.08,
                        "z": -3.6475125457779702
                    },
                    "rotation": {
                        "x": 90,
                        "y": 180,
                        "z": 0
                    }
                }
            ]
        },
        {
            "id": "sturdy_box_small",
            "type": "chest_1",
            "salientMaterials": [
                "plastic"
            ],
            "materials": [
                "UnityAssetStore/Kindergarten_Interior/Models/Materials/color 3"
            ],
            "shows": [
                {
                    "stepBegin": 0,
                    "position": {
                        "x": 3.677714401765291,
                        "y": 0,
                        "z": -4.5058322476845
                    },
                    "rotation": {
                        "x": 0,
                        "y": 180,
                        "z": 0
                    },
                    "scale": {
                        "x": 0.35,
                        "y": 0.35,
                        "z": 0.35
                    }
                }
            ]
        },
        {
            "id": "suitcase_med",
            "type": "suitcase_1",
            "salientMaterials": [
                "metal"
            ],
            "materials": [
                "AI2-THOR/Materials/Metals/WhiteMetal"
            ],
            "shows": [
                {
                    "stepBegin": 0,
                    "position": {
                        "x": 1.5,
                        "y": 0,
                        "z": 0
                    },
                    "rotation": {
                        "x": 0,
                        "y": 0,
                        "z": 0
                    },
                    "scale": {
                        "x": 1.25,
                        "y": 1.25,
                        "z": 1.25
                    }
                }
            ]
        }
    ],
    "goal": {
        "category": "retrieval",
        "description": "Find and pick up the trophy.",
        "last_step": 3000,
        "metadata": {
            "target": {
                "id": "trophy",
                "image": null
            }
        }
    },
    "answer": {}
}